multivariateach/__init__.py
multivariateach/multivariateach.py
tests/__init__.py
tests/test_multivariteach.py
MultivariaTeach-0.1.11.dist-info/LICENSE
MultivariaTeach-0.1.11.dist-info/METADATA
MultivariaTeach-0.1.11.dist-info/WHEEL
MultivariaTeach-0.1.11.dist-info/top_level.txt
MultivariaTeach-0.1.11.dist-info/RECORD
