Metadata-Version: 2.1
Name: MultivariaTeach
Version: 0.1.11
Summary: A collection of tools intended for students of multivariate analysis
Home-page: https://github.com/Ben-Goren/MultivariaTeach
Author: Ben Goren
Author-email: bgoren@asu.edu
Classifier: Development Status :: 4 - Beta
Classifier: Intended Audience :: Education
Classifier: License :: OSI Approved :: ISC License (ISCL)
Classifier: Programming Language :: Python :: 3
Classifier: Programming Language :: Python :: 3.7
Classifier: Programming Language :: Python :: 3.8
Classifier: Programming Language :: Python :: 3.9
Requires-Python: >=3.7
License-File: LICENSE
Requires-Dist: numpy >=1.19.5
Requires-Dist: scipy >=1.5.0
Requires-Dist: pandas >=1.2.0
